pyilint/__init__.py
pyilint-0.2.2.dist-info/LICENSE
pyilint-0.2.2.dist-info/METADATA
pyilint-0.2.2.dist-info/WHEEL
pyilint-0.2.2.dist-info/top_level.txt
pyilint-0.2.2.dist-info/RECORD
