Metadata-Version: 2.1
Name: pyilint
Version: 0.2.2
Summary: Pure Python implementation of InterlockLedger ILInt standard
Home-page: https://github.com/interlockledger/pyilint
Author: InterlockLedger Network
Author-email: fchino@il2.io
Project-URL: Bug Tracker, https://github.com/interlockledger/pyilint/issues
Classifier: Programming Language :: Python :: 3
Classifier: License :: OSI Approved :: MIT License
Classifier: Operating System :: OS Independent
Requires-Python: >=3.6
License-File: LICENSE
